ccnpy/__init__.py
ccnpy/apps/__init__.py
ccnpy/apps/cli_utils.py
ccnpy/apps/manifest_reader.py
ccnpy/apps/manifest_writer.py
ccnpy/apps/packet_reader.py
ccnpy/apps/packet_utils.py
ccnpy/core/ContentObject.py
ccnpy/core/DisplayFormatter.py
ccnpy/core/ExpiryTime.py
ccnpy/core/FinalChunkId.py
ccnpy/core/FixedHeader.py
ccnpy/core/HashTlvType.py
ccnpy/core/HashValue.py
ccnpy/core/Interest.py
ccnpy/core/KeyId.py
ccnpy/core/KeyLink.py
ccnpy/core/Link.py
ccnpy/core/Name.py
ccnpy/core/Packet.py
ccnpy/core/PacketValidator.py
ccnpy/core/Pad.py
ccnpy/core/Payload.py
ccnpy/core/PayloadType.py
ccnpy/core/Serializable.py
ccnpy/core/SignatureTime.py
ccnpy/core/Timestamp.py
ccnpy/core/Tlv.py
ccnpy/core/TlvType.py
ccnpy/core/ValidationAlg.py
ccnpy/core/ValidationPayload.py
ccnpy/core/__init__.py
ccnpy/crypto/AeadKey.py
ccnpy/crypto/Crc32c.py
ccnpy/crypto/DecryptionError.py
ccnpy/crypto/HpkeKdfIdentifiers.py
ccnpy/crypto/InsecureKeystore.py
ccnpy/crypto/KDF.py
ccnpy/crypto/RsaKey.py
ccnpy/crypto/RsaSha256.py
ccnpy/crypto/Signer.py
ccnpy/crypto/Verifier.py
ccnpy/crypto/__init__.py
ccnpy/exceptions/CannotParseError.py
ccnpy/exceptions/ParseError.py
ccnpy/exceptions/__init__.py
ccnpy/flic/HashGroupBuilder.py
ccnpy/flic/ManifestDecryptor.py
ccnpy/flic/ManifestEncryptor.py
ccnpy/flic/ManifestFactory.py
ccnpy/flic/ManifestTree.py
ccnpy/flic/ManifestTreeOptions.py
ccnpy/flic/RsaOaepCtx/HashAlg.py
ccnpy/flic/RsaOaepCtx/Readme.md
ccnpy/flic/RsaOaepCtx/RsaOaepDecryptor.py
ccnpy/flic/RsaOaepCtx/RsaOaepEncryptor.py
ccnpy/flic/RsaOaepCtx/RsaOaepImpl.py
ccnpy/flic/RsaOaepCtx/RsaOaepWrapper.py
ccnpy/flic/RsaOaepCtx/WrappedKey.py
ccnpy/flic/RsaOaepCtx/__init__.py
ccnpy/flic/__init__.py
ccnpy/flic/aeadctx/AeadData.py
ccnpy/flic/aeadctx/AeadDecryptor.py
ccnpy/flic/aeadctx/AeadEncryptor.py
ccnpy/flic/aeadctx/AeadImpl.py
ccnpy/flic/aeadctx/AeadParameters.py
ccnpy/flic/aeadctx/__init__.py
ccnpy/flic/name_constructor/FileMetadata.py
ccnpy/flic/name_constructor/HashSchemaImpl.py
ccnpy-0.1.4.dist-info/LICENSE
ccnpy-0.1.4.dist-info/METADATA
ccnpy-0.1.4.dist-info/WHEEL
ccnpy-0.1.4.dist-info/entry_points.txt
ccnpy-0.1.4.dist-info/RECORD
