Metadata-Version: 2.3
Name: ccnpy
Version: 0.1.4
Summary: A pure python implementation of the CCNx client.
License: Apache 2.0
Keywords: CCNx,ICN,Information Centric Networking
Author: Marc Mosko
Author-email: marc@mosko.org
Requires-Python: >=3.13
Classifier: Programming Language :: Python :: 3
Classifier: License :: OSI Approved :: Apache Software License
Classifier: Operating System :: OS Independent
Classifier: Development Status :: 4 - Beta
Classifier: Topic :: System :: Networking
Requires-Dist: coverage (>=7.6.4)
Requires-Dist: crc32c (>=2.7.1)
Requires-Dist: cryptography (>=43.0.1)
Requires-Dist: jsbeautifier (>=1.15.1)
Requires-Dist: matplotlib (>=3.9.2)
Requires-Dist: networkx (>=3.4.2)
Requires-Dist: pydot (>=3.0.2)
Requires-Dist: pytest (>=8.3.3)
Project-URL: Homepage, https://github.com/mmosko/ccnpy
Project-URL: Issues, https://github.com/mmosko/ccnpy/issues
